page_rank_engine/__init__.py
page_rank_engine/page_rank.py
page_rank_engine-0.2.0.dist-info/METADATA
page_rank_engine-0.2.0.dist-info/WHEEL
page_rank_engine-0.2.0.dist-info/top_level.txt
page_rank_engine-0.2.0.dist-info/RECORD
